README.rst
setup.py
biolxyUtil/__init__.py
biolxyUtil/base.py
biolxyUtil/df.py
biolxyUtil.egg-info/PKG-INFO
biolxyUtil.egg-info/SOURCES.txt
biolxyUtil.egg-info/dependency_links.txt
biolxyUtil.egg-info/entry_points.txt
biolxyUtil.egg-info/top_level.txt